versionkit/__init__.py
versionkit-0.1.0.dist-info/WHEEL
versionkit-0.1.0.dist-info/METADATA
versionkit-0.1.0.dist-info/RECORD
