Metadata-Version: 2.1
Name: versionkit
Version: 0.1.0
Summary: 
Author: Edward George
Author-email: edwardgeorge@gmail.com
Requires-Python: >=3.7,<4.0
Classifier: Programming Language :: Python :: 3
Classifier: Programming Language :: Python :: 3.7
Classifier: Programming Language :: Python :: 3.8
Requires-Dist: tomlkit (>=0.6.0,<0.7.0)
